README.md
setup.py
pongpy/__init__.py
pongpy/cmd.py
pongpy/definitions.py
pongpy/pong.py
pongpy/sounds.py
pongpy.egg-info/PKG-INFO
pongpy.egg-info/SOURCES.txt
pongpy.egg-info/dependency_links.txt
pongpy.egg-info/entry_points.txt
pongpy.egg-info/requires.txt
pongpy.egg-info/top_level.txt
pongpy/controllers/__init__.py
pongpy/controllers/ball.py
pongpy/controllers/board.py
pongpy/controllers/team_manager.py
pongpy/interfaces/__init__.py
pongpy/interfaces/team.py
pongpy/models/__init__.py
pongpy/models/color.py
pongpy/models/game_info.py
pongpy/models/pos.py
pongpy/models/state.py
pongpy/teams/__init__.py
pongpy/teams/follow_team.py
pongpy/teams/manual_team.py
pongpy/teams/random_team.py
pongpy/teams/stub_team.py