Metadata-Version: 1.0
Name: pongpy
Version: 0.2.2
Summary: Pong game
Home-page: https://github.com/pistatium/pong
Author: pistatium
Author-email: UNKNOWN
License: MIT
Platform: UNKNOWN
